{
  "schema_version": "2.0.0",
  "platform_id": "platform:synthetic-platform",
  "journey_id": "journey:synthetic-platform:documented-primary",
  "analysis_mode": "specific-attempt",
  "analysis_status": "supported-hypothesis",
  "headline": "One synthetic hypothesis passes both evidence gates for this synthetic attempt.",
  "what_we_know": [
    {
      "statement": "A direct observation recorded the attempt boundary.",
      "evidence_state": "directly-observed",
      "source_ids": []
    }
  ],
  "what_may_be_happening": [
    {
      "statement": "The synthetic credential hypothesis is supported for this attempt.",
      "blocker_ids": ["blocker:U99.01"],
      "evidence_state": "supported",
      "source_ids": ["research:synthetic-card"],
      "evidence_event_ids": ["event:direct-observation"],
      "evidence_kinds": ["direct_observation"],
      "limitations": ["Support applies only to this synthetic attempt and does not establish prevalence or causation elsewhere."]
    }
  ],
  "what_we_do_not_know": ["Whether the same condition occurs in another attempt."],
  "next_check": "Repeat the same observation with a separately selected participant.",
  "comparison": {
    "summary": null,
    "comparison_record_ids": [],
    "limitations": ["Comparison is outside this synthetic diagnosis example."],
    "analysis_eligible": false,
    "minimum_comparison_count_met": false,
    "pattern_claim_eligible": false,
    "safe_to_anonymize": false,
    "withheld_reasons": ["No comparison record was supplied."]
  },
  "source_ids": ["research:synthetic-card"],
  "limitations": ["Synthetic contract example. It does not promote any real catalog reason."]
}
