{
  "schema_version": "1.0",
  "platform": {
    "name": "Netlify",
    "slug": "netlify",
    "category": "Cloud and application runtimes"
  },
  "audit_status": "needs-human-judgment",
  "audited_at": "2026-07-22",
  "source_record_sha256": "5e17118be52e4673fb6ef9cf779a09e75a81697abaaf9f57f9ae3b5dca693897",
  "starting_state": {
    "boundary": "account creation",
    "assumptions": [
      "The developer has an existing web project folder containing HTML, CSS, JavaScript, or framework source.",
      "The developer has a supported browser and reliable network connection.",
      "For the logged-in drag-and-drop candidate, the developer has a Netlify account and can access the intended team. An anonymous branch exists but behaves differently for unbuilt source.",
      "If the folder is dropped anonymously, it must already be built because Netlify publishes anonymous files as-is."
    ]
  },
  "developer_goal": "Publish an existing web project on Netlify and open its live preview URL.",
  "first_success": {
    "outcome": "Dropped project is deployed and available at its live netlify.app URL.",
    "observable_signal": "Opening the Preview/live URL ending in netlify.app serves the published site.",
    "source_ids": [
      "S2"
    ]
  },
  "route_selection": {
    "surface": "Publish an existing folder through logged-in Netlify Drop",
    "rule": "Prefer the official first-deploy tutorial path without duplicating steps or splitting form fields into separate required path steps.",
    "selected": "Publish an existing folder through logged-in Netlify Drop",
    "candidates": [
      {
        "name": "Publish an existing folder through logged-in Netlify Drop",
        "status": "selected",
        "reason": "Netlify Start from files / Drop path publishes a local folder to a live netlify.app URL. Removed a duplicated copy of the same path that previously inflated step counts."
      }
    ]
  },
  "required_path": [
    {
      "step_number": 1,
      "kind": "product-interaction",
      "interface": "other",
      "action": "Open the Netlify documentation home and select Create a new project.",
      "required_fields": [],
      "observable_result": "The project-start choices are visible.",
      "evidence_state": "documented",
      "source_ids": [
        "S1"
      ]
    },
    {
      "step_number": 2,
      "kind": "implementation",
      "interface": "other",
      "action": "Open Choose your path and select Start from files for a complete drag-and-drop candidate.",
      "required_fields": [],
      "observable_result": "The page explains the account, Drop publisher, folder, and preview URL sequence.",
      "evidence_state": "documented",
      "source_ids": [
        "S2"
      ]
    },
    {
      "step_number": 3,
      "kind": "implementation",
      "interface": "other",
      "action": "Prepare the local project folder to deploy.",
      "required_fields": [],
      "observable_result": "The folder is unzipped and includes the project files; for anonymous publishing it already contains built files.",
      "evidence_state": "documented",
      "source_ids": [
        "S2"
      ]
    },
    {
      "step_number": 4,
      "kind": "account",
      "interface": "browser",
      "action": "Log in to the Netlify account and select the team that should manage the project.",
      "required_fields": [],
      "observable_result": "The team-owned Projects page or Netlify Drop publisher can be opened.",
      "evidence_state": "documented",
      "source_ids": [
        "S2",
        "S3"
      ]
    },
    {
      "step_number": 5,
      "kind": "implementation",
      "interface": "browser",
      "action": "Open the Netlify Drop publisher or scroll to the drag-and-drop section at the bottom of the team's Projects page.",
      "required_fields": [],
      "observable_result": "The folder drop target is ready.",
      "evidence_state": "documented",
      "source_ids": [
        "S2",
        "S5"
      ]
    },
    {
      "step_number": 6,
      "kind": "verification",
      "interface": "browser",
      "action": "Drag the project folder into the Deploy zone.",
      "required_fields": [],
      "observable_result": "The upload and deploy process begins.",
      "evidence_state": "documented",
      "source_ids": [
        "S2",
        "S5"
      ]
    },
    {
      "step_number": 7,
      "kind": "verification",
      "interface": "other",
      "action": "For a logged-in source folder, detect the framework, run the build if needed, and publish the result; for prebuilt output, publish the supplied files.",
      "required_fields": [],
      "observable_result": "The project dashboard shows a Preview URL ending in netlify.app.",
      "evidence_state": "documented",
      "source_ids": [
        "S2",
        "S5",
        "S6",
        "S8"
      ]
    },
    {
      "step_number": 8,
      "kind": "verification",
      "interface": "browser",
      "action": "Open the Preview URL shown in the project dashboard.",
      "required_fields": [],
      "observable_result": "The intended project is visible at the Preview URL and the official guide says it is now published on the web.",
      "evidence_state": "documented",
      "source_ids": [
        "S2",
        "S8"
      ]
    }
  ],
  "prerequisites": [
    {
      "description": "For the managed drag-and-drop route, a Netlify account authenticated into the team that should own the project. The public docs link to signup but do not reconstruct its current atomic screens or verification order.",
      "source_ids": [
        "S2",
        "S3"
      ]
    },
    {
      "description": "A current Chromium-based browser is recommended for drag-and-drop troubleshooting.",
      "source_ids": [
        "S2"
      ]
    },
    {
      "description": "A local web project folder. A ZIP archive must be unzipped first.",
      "source_ids": [
        "S2"
      ]
    },
    {
      "description": "If deploying anonymously or using manual deployment without a build, the folder must contain already built output. A logged-in drop can let Netlify detect a framework and run its build.",
      "source_ids": [
        "S2",
        "S5"
      ]
    },
    {
      "description": "A current Free credit-based plan is sufficient for a first production deployment while credits remain. A production deployment consumes 15 credits.",
      "source_ids": [
        "S6"
      ]
    }
  ],
  "external_gates": [
    {
      "description": "Netlify presents several peer starting routes and does not select a universal default.",
      "source_ids": [
        "S1",
        "S2"
      ]
    },
    {
      "description": "The correct folder depends on whether the developer is logged in. Anonymous drops publish files as-is, while logged-in drops can detect and build a framework project.",
      "source_ids": [
        "S2"
      ]
    },
    {
      "description": "The managed route requires login, but the linked signup flow is not atomically documented on the public Start pages.",
      "source_ids": [
        "S2",
        "S3"
      ]
    },
    {
      "description": "The docs say deploys under 50 MB work best and that individual files over 10 MB can cause a stuck deploy.",
      "source_ids": [
        "S2"
      ]
    },
    {
      "description": "Network reliability, browser version, and local free memory can block upload. The troubleshooting baseline suggests roughly four times the uncompressed project size in free memory.",
      "source_ids": [
        "S2"
      ]
    },
    {
      "description": "Netlify may need to detect, build, and publish the project before the Preview URL is available. No typical duration is documented for this route.",
      "source_ids": [
        "S2",
        "S8"
      ]
    },
    {
      "description": "A production deployment consumes 15 credits. The Free plan includes 300 monthly credits with a hard limit.",
      "source_ids": [
        "S6"
      ]
    }
  ],
  "unavoidable_waits": [],
  "platform_outcomes": [
    {
      "description": "Dropped project is deployed and available at its live netlify.app URL.",
      "source_ids": [
        "S1"
      ]
    }
  ],
  "excluded": [
    {
      "item": "Inflated duplicate or over-split steps",
      "reason": "Path compacted to the official first-success tutorial structure.",
      "source_ids": [
        "S1"
      ]
    }
  ],
  "sources": [
    {
      "id": "S1",
      "title": "Netlify Documentation",
      "url": "https://docs.netlify.com/",
      "source_type": "official-documentation",
      "accessed_at": "2026-07-18",
      "evidence_supported": [
        "Official entry surface",
        "Peer AI, Git and drag-and-drop routes"
      ]
    },
    {
      "id": "S2",
      "title": "Choose your path",
      "url": "https://docs.netlify.com/start/choose-your-path/",
      "source_type": "official-documentation",
      "accessed_at": "2026-07-18",
      "evidence_supported": [
        "Route plurality",
        "Complete drag-and-drop path",
        "Preview URL terminal",
        "Build-state branches",
        "Upload limits and troubleshooting"
      ]
    },
    {
      "id": "S3",
      "title": "Deploy from your repository",
      "url": "https://docs.netlify.com/start/quickstarts/deploy-from-repository/",
      "source_type": "official-documentation",
      "accessed_at": "2026-07-18",
      "evidence_supported": [
        "Git route steps",
        "Account requirement",
        "Provider authorization",
        "Publish settings",
        "Optional domain checkpoint"
      ]
    },
    {
      "id": "S4",
      "title": "Deploy from AI code generation tool",
      "url": "https://docs.netlify.com/start/quickstarts/deploy-from-ai-code-generation-tool/",
      "source_type": "official-documentation",
      "accessed_at": "2026-07-18",
      "evidence_supported": [
        "Official drag-and-drop recommendation for AI-generated projects",
        "Account optionality",
        "Anonymous CLI path",
        "One-hour claim deadline"
      ]
    },
    {
      "id": "S5",
      "title": "Create deploys",
      "url": "https://docs.netlify.com/deploy/create-deploys/",
      "source_type": "official-documentation",
      "accessed_at": "2026-07-18",
      "evidence_supported": [
        "Manual deployment behavior",
        "Anonymous live project",
        "Drag-and-drop entry",
        "No-build statement"
      ]
    },
    {
      "id": "S6",
      "title": "Credit-based pricing plans",
      "url": "https://docs.netlify.com/manage/accounts-and-billing/billing/billing-for-credit-based-plans/credit-based-pricing-plans/",
      "source_type": "official-documentation",
      "accessed_at": "2026-07-18",
      "evidence_supported": [
        "Free plan allowance",
        "Production deployment credit cost",
        "Failed deploy credit behavior"
      ]
    },
    {
      "id": "S7",
      "title": "Netlify Website Terms of Use",
      "url": "https://www.netlify.com/legal/terms-of-use/",
      "source_type": "official-documentation",
      "accessed_at": "2026-07-18",
      "evidence_supported": [
        "Netlify, Inc. official organization name"
      ]
    },
    {
      "id": "S8",
      "title": "Netlify Glossary for Beginners",
      "url": "https://docs.netlify.com/start/glossary/",
      "source_type": "official-documentation",
      "accessed_at": "2026-07-18",
      "evidence_supported": [
        "Instant and seconds-level Netlify Drop time claim",
        "Build before publish model",
        "Failed build produces no deploy",
        "Deploy as live availability"
      ]
    }
  ],
  "uncertainties": [
    {
      "question": "Which of AI agent, Git repository, framework starter, template, drag and drop, or CLI is Netlify's single canonical first route?",
      "impact": "Different entrants face materially different plans, credentials, authorization, local tooling, and first-success terminals.",
      "evidence_needed": "The documentation home and Choose your path explicitly present multiple routes and do not rank one as universal."
    },
    {
      "question": "What is the current atomic Netlify account signup and verification sequence?",
      "impact": "The logged-in route can contain additional fields, authentication choices, email verification, terms, or team creation before the first deploy.",
      "evidence_needed": "The official quickstarts link to the application signup page but the public documentation inspected does not reconstruct its current steps."
    },
    {
      "question": "Does the current logged-in Drop publisher always run a framework build for unbuilt source?",
      "impact": "The required local preparation and wait or failure states differ between source and output folders.",
      "evidence_needed": "Choose your path says logged-in drops can detect and build, while Create deploys states that manual deployment does not run a build command."
    }
  ],
  "counts": null
}
