{
  "schema_version": "1.0",
  "platform": {
    "name": "Porter",
    "slug": "porter",
    "category": "Cloud and application runtimes"
  },
  "audit_status": "needs-human-judgment",
  "audited_at": "2026-07-22",
  "source_record_sha256": "d432d9400d1ddaf8af61ee8ac338f6ee84f4b8a7ba72d51027e7b58c11e1f01f",
  "starting_state": {
    "boundary": "account creation",
    "assumptions": [
      "The developer has a supported browser and can receive email when the selected route requires it.",
      "No platform account, tenant, credentials, or product resources exist yet.",
      "Developer has an active cloud provider account (AWS, GCP, or Azure) with admin or owner permissions",
      "Developer has a deployable application with a start command or Dockerfile, pushed to GitHub or container registry"
    ]
  },
  "developer_goal": "Deploy their first application on Porter",
  "first_success": {
    "outcome": "Developer successfully deploys their application and accesses it live on a public URL",
    "observable_signal": "Application is live and accessible at *.onporter.run URL shown in the Porter dashboard",
    "source_ids": [
      "S1"
    ]
  },
  "route_selection": {
    "surface": "Porter Web Dashboard and CLI",
    "rule": "Reconstruct complete official candidate routes, prefer no payment/admin/approval when possible, then minimize required actions; leave consequential ties unresolved.",
    "selected": null,
    "candidates": [
      {
        "name": "CLI-based bundle installation",
        "status": "unresolved",
        "reason": "Present in the machine draft; not selected by an independent shortest-path audit."
      },
      {
        "name": "Porter CLI",
        "status": "unresolved",
        "reason": "CLI is used mainly for bundle installation and management after initial setup; the first-mile onboarding focuses on the web dashboard for project creation and app deployment."
      }
    ]
  },
  "required_path": [
    {
      "step_number": 1,
      "kind": "account",
      "interface": "web-ui",
      "action": "Create a Porter account and project",
      "required_fields": [
        {
          "label": "Project name",
          "field_type": "other",
          "evidence_state": "unverified",
          "source_ids": [
            "S1"
          ],
          "notes": "Mapped from machine-drafted primary_path; field inventory not independently audited."
        }
      ],
      "observable_result": "Project creation confirmation in dashboard",
      "evidence_state": "unverified",
      "source_ids": [
        "S1"
      ]
    },
    {
      "step_number": 2,
      "kind": "product-interaction",
      "interface": "web-ui",
      "action": "Select cloud provider to provision infrastructure",
      "required_fields": [
        {
          "label": "Cloud provider selection",
          "field_type": "other",
          "evidence_state": "unverified",
          "source_ids": [
            "S1"
          ],
          "notes": "Mapped from machine-drafted primary_path; field inventory not independently audited."
        }
      ],
      "observable_result": "Cloud provider selection confirmed in UI",
      "evidence_state": "unverified",
      "source_ids": [
        "S1"
      ]
    },
    {
      "step_number": 3,
      "kind": "product-interaction",
      "interface": "web-ui",
      "action": "Set up Kubernetes cluster in selected cloud account",
      "required_fields": [
        {
          "label": "AWS Account ID and cluster configuration",
          "field_type": "other",
          "evidence_state": "unverified",
          "source_ids": [
            "S1"
          ],
          "notes": "Mapped from machine-drafted primary_path; field inventory not independently audited."
        }
      ],
      "observable_result": "Cluster ready notification in dashboard",
      "evidence_state": "unverified",
      "source_ids": [
        "S1"
      ]
    },
    {
      "step_number": 4,
      "kind": "product-interaction",
      "interface": "web-ui",
      "action": "Create first application deployment",
      "required_fields": [
        {
          "label": "GitHub repository and branch selection",
          "field_type": "other",
          "evidence_state": "unverified",
          "source_ids": [
            "S1"
          ],
          "notes": "Mapped from machine-drafted primary_path; field inventory not independently audited."
        }
      ],
      "observable_result": "Toast notification with View PR button and warning banner with Merge PR link",
      "evidence_state": "unverified",
      "source_ids": [
        "S1"
      ]
    },
    {
      "step_number": 5,
      "kind": "implementation",
      "interface": "other",
      "action": "Merge GitHub Actions PR to trigger build and deployment",
      "required_fields": [
        {
          "label": "Merged PR",
          "field_type": "other",
          "evidence_state": "unverified",
          "source_ids": [
            "S1"
          ],
          "notes": "Mapped from machine-drafted primary_path; field inventory not independently audited."
        }
      ],
      "observable_result": "Build logs and deployment progress visible in Porter dashboard",
      "evidence_state": "unverified",
      "source_ids": [
        "S1"
      ]
    },
    {
      "step_number": 6,
      "kind": "implementation",
      "interface": "web-ui",
      "action": "View running application and access public URL",
      "required_fields": [
        {
          "label": "Deployed application",
          "field_type": "other",
          "evidence_state": "unverified",
          "source_ids": [
            "S1"
          ],
          "notes": "Mapped from machine-drafted primary_path; field inventory not independently audited."
        }
      ],
      "observable_result": "Application is live and accessible",
      "evidence_state": "unverified",
      "source_ids": [
        "S1"
      ]
    }
  ],
  "prerequisites": [
    {
      "description": "Active cloud provider account (AWS, GCP, or Azure) with admin or owner permissions to provision infrastructure",
      "source_ids": [
        "S1"
      ]
    },
    {
      "description": "Deployable application with a start command or Dockerfile, pushed to a GitHub repository or container registry",
      "source_ids": [
        "S1"
      ]
    }
  ],
  "external_gates": [
    {
      "description": "Creating a Porter account and project requires valid project name and successful account creation",
      "source_ids": [
        "S1"
      ]
    },
    {
      "description": "Cloud provider account must have admin or owner permissions to create Kubernetes clusters and IAM roles",
      "source_ids": [
        "S1"
      ]
    },
    {
      "description": "For AWS, user must acknowledge IAM resource creation in CloudFormation and create the stack",
      "source_ids": [
        "S1"
      ]
    },
    {
      "description": "User must review and accept estimated monthly costs for infrastructure provisioning",
      "source_ids": [
        "S1"
      ]
    },
    {
      "description": "Connecting GitHub requires authorizing the Porter GitHub App and selecting repository access",
      "source_ids": [
        "S1"
      ]
    },
    {
      "description": "User must merge the GitHub Actions PR to trigger deployment",
      "source_ids": [
        "S1"
      ]
    }
  ],
  "unavoidable_waits": [],
  "platform_outcomes": [
    {
      "description": "Application is deployed and accessible via a public URL on Porter",
      "source_ids": [
        "S1"
      ]
    }
  ],
  "excluded": [],
  "sources": [
    {
      "id": "S1",
      "title": "Quickstart",
      "url": "https://docs.porter.run/getting-started/quickstart",
      "source_type": "official-documentation",
      "accessed_at": "2026-07-22",
      "evidence_supported": [
        "Quickstart",
        "Prerequisites",
        "Step 1: Sign up and create a project",
        "Step 2: Select your cloud provider"
      ]
    },
    {
      "id": "S6",
      "title": "Quickstart – Porter CLI bundle installation",
      "url": "https://porter.sh/docs/quickstart/",
      "source_type": "official-documentation",
      "accessed_at": "2026-07-22",
      "evidence_supported": [
        "Quickstart – Porter CLI bundle installation",
        "Install Porter",
        "Install a Bundle",
        "List Bundle Installations"
      ]
    }
  ],
  "uncertainties": [
    {
      "question": "What are the detailed cluster setup steps and requirements for GCP and Azure cloud providers?",
      "impact": "Potential differences in friction gates, permissions, and provisioning steps could affect onboarding experience and time to first success.",
      "evidence_needed": "The official quickstart documentation details AWS cluster setup extensively but only mentions GCP and Azure without detailed steps."
    },
    {
      "question": "Is there an officially documented time estimate for time to first success from account creation to live application?",
      "impact": "Knowing exact time expectations helps set user expectations and measure onboarding efficiency.",
      "evidence_needed": "The documentation states 'Deploy your first application to Porter in minutes' but does not provide a precise or vendor-claimed time."
    },
    {
      "question": "Has the machine-drafted Porter route been independently shortest-path audited?",
      "impact": "Action counts and peer comparison must stay withheld until a human audit passes.",
      "evidence_needed": "Complete a shortest-path audit against current official docs and mark verified only when evidence supports it."
    }
  ],
  "counts": null
}
