{
  "schema_version": "1.0",
  "platform": {
    "name": "Render",
    "slug": "render",
    "category": "Cloud and application runtimes"
  },
  "audit_status": "needs-human-judgment",
  "audited_at": "2026-07-22",
  "source_record_sha256": "a05e76cf2323d9332d27876e28e709c343a5303ca2d6967f056cea9a842c32d6",
  "starting_state": {
    "boundary": "account creation",
    "assumptions": [
      "A GitHub, GitLab, or Bitbucket repository already contains the web app to deploy.",
      "No Render account or Live Web Service is assumed.",
      "No Render CLI install is assumed for the Dashboard path."
    ]
  },
  "developer_goal": "Sign up for Render, connect a Git provider, deploy a server-side Web Service from a repository, and open the Live onrender.com URL.",
  "first_success": {
    "outcome": "Web Service deploy is Live and the onrender.com URL serves the app root content.",
    "observable_signal": "The service shows Live status and opening the onrender.com URL returns the deployed app's root-path content.",
    "source_ids": [
      "S2",
      "S4"
    ]
  },
  "route_selection": {
    "surface": "Your First Render Deploy, Dashboard Web Service",
    "rule": "Prefer the official first-deploy tutorial path without duplicating steps or splitting form fields into separate required path steps.",
    "selected": "Your First Render Deploy, Dashboard Web Service",
    "candidates": [
      {
        "name": "Your First Render Deploy, Dashboard Web Service",
        "status": "selected",
        "reason": "Render's Your First Render Deploy tutorial is the official first-app path. It documents free resources with no payment required, and the Dashboard tab is the first deployment method shown for creating a Web Service from a connected Git repo"
      }
    ]
  },
  "required_path": [
    {
      "step_number": 1,
      "kind": "product-interaction",
      "interface": "other",
      "action": "Open Your First Render Deploy and follow the Dashboard deployment path for a Web Service.",
      "required_fields": [],
      "observable_result": "Signup, Git connection, and Deploy sections are visible.",
      "evidence_state": "documented",
      "source_ids": [
        "S2"
      ]
    },
    {
      "step_number": 2,
      "kind": "account",
      "interface": "browser",
      "action": "Sign up for a free Render account.",
      "required_fields": [],
      "observable_result": "The Dashboard and Account Settings are reachable.",
      "evidence_state": "documented",
      "source_ids": [
        "S2",
        "S7"
      ]
    },
    {
      "step_number": 3,
      "kind": "account",
      "interface": "browser",
      "action": "Connect a Git provider under Account Settings \u2192 Git Deployment Credentials.",
      "required_fields": [],
      "observable_result": "The provider appears under Git Deployment Credentials.",
      "evidence_state": "documented",
      "source_ids": [
        "S2",
        "S5",
        "S6"
      ]
    },
    {
      "step_number": 4,
      "kind": "implementation",
      "interface": "web-ui",
      "action": "Create a Web Service from the connected Git repository.",
      "required_fields": [],
      "observable_result": "The Deploy action is available on the completed form.",
      "evidence_state": "documented",
      "source_ids": [
        "S2",
        "S3",
        "S4"
      ]
    },
    {
      "step_number": 5,
      "kind": "verification",
      "interface": "web-ui",
      "action": "Click Deploy to create the Web Service and start the first build.",
      "required_fields": [],
      "observable_result": "Deploy logs are visible for the new service.",
      "evidence_state": "documented",
      "source_ids": [
        "S2"
      ]
    },
    {
      "step_number": 6,
      "kind": "verification",
      "interface": "web-ui",
      "action": "Wait until the deploy is Live, then open the service's onrender.com URL and confirm the app's root content.",
      "required_fields": [],
      "observable_result": "The service is Live and the onrender.com URL serves the root-path content.",
      "evidence_state": "documented",
      "source_ids": [
        "S2",
        "S4"
      ]
    }
  ],
  "prerequisites": [
    {
      "description": "A GitHub, GitLab, or Bitbucket account with a repository containing the web app; this route uses GitHub.",
      "source_ids": [
        "S2",
        "S5"
      ]
    },
    {
      "description": "Permission to authorize Render to access the selected repositories.",
      "source_ids": [
        "S2",
        "S5"
      ]
    },
    {
      "description": "A server-side web app that listens for HTTP requests and binds its public HTTP server to 0.0.0.0 on the port Render provides.",
      "source_ids": [
        "S2",
        "S4"
      ]
    },
    {
      "description": "The application build command, start command, and any required environment variables.",
      "source_ids": [
        "S2"
      ]
    },
    {
      "description": "A payment method is not required for the tutorial Free instance path.",
      "source_ids": [
        "S2"
      ]
    }
  ],
  "external_gates": [
    {
      "description": "A Render account is required before Dashboard deploy actions.",
      "source_ids": [
        "S2",
        "S7"
      ]
    },
    {
      "description": "The developer must authorize Render to access the selected Git repositories.",
      "source_ids": [
        "S2",
        "S5"
      ]
    },
    {
      "description": "The tutorial requires choosing Web Service or Static Site, then completing service-specific form fields.",
      "source_ids": [
        "S2",
        "S3"
      ]
    },
    {
      "description": "Build command, start command, runtime, and any required environment variables must match the application.",
      "source_ids": [
        "S2"
      ]
    },
    {
      "description": "The first build and deploy must finish before the service is Live.",
      "source_ids": [
        "S2"
      ]
    },
    {
      "description": "Free web services spin down after 15 minutes of inactivity and spin back up on the next request.",
      "source_ids": [
        "S2"
      ]
    }
  ],
  "unavoidable_waits": [],
  "platform_outcomes": [
    {
      "description": "Web Service deploy is Live and the onrender.com URL serves the app root content.",
      "source_ids": [
        "S1"
      ]
    }
  ],
  "excluded": [
    {
      "item": "Inflated duplicate or over-split steps",
      "reason": "Path compacted to the official first-success tutorial structure.",
      "source_ids": [
        "S1"
      ]
    }
  ],
  "sources": [
    {
      "id": "S1",
      "title": "Render documentation home",
      "url": "https://render.com/docs",
      "source_type": "official-documentation",
      "accessed_at": "2026-07-22",
      "evidence_supported": [
        "Entry to first-deploy docs"
      ]
    },
    {
      "id": "S2",
      "title": "Your First Render Deploy",
      "url": "https://render.com/docs/your-first-deploy",
      "source_type": "official-documentation",
      "accessed_at": "2026-07-22",
      "evidence_supported": [
        "Free resources, no payment required",
        "Git credential connection",
        "Web Service form fields",
        "Deploy then open Live URL"
      ]
    },
    {
      "id": "S3",
      "title": "Service types",
      "url": "https://render.com/docs/service-types",
      "source_type": "official-documentation",
      "accessed_at": "2026-07-22",
      "evidence_supported": [
        "Web Service versus Static Site"
      ]
    },
    {
      "id": "S4",
      "title": "Web Services",
      "url": "https://render.com/docs/web-services",
      "source_type": "official-documentation",
      "accessed_at": "2026-07-22",
      "evidence_supported": [
        "Web Service deploy behavior",
        "0.0.0.0 binding expectation"
      ]
    },
    {
      "id": "S5",
      "title": "GitHub on Render",
      "url": "https://render.com/docs/github",
      "source_type": "official-documentation",
      "accessed_at": "2026-07-22",
      "evidence_supported": [
        "GitHub authorization for deploys"
      ]
    },
    {
      "id": "S6",
      "title": "Login settings",
      "url": "https://render.com/docs/login-settings",
      "source_type": "official-documentation",
      "accessed_at": "2026-07-22",
      "evidence_supported": [
        "Account Settings credential management"
      ]
    },
    {
      "id": "S7",
      "title": "Render register",
      "url": "https://dashboard.render.com/register",
      "source_type": "official-documentation",
      "accessed_at": "2026-07-22",
      "evidence_supported": [
        "Free account signup entry"
      ]
    }
  ],
  "uncertainties": [
    {
      "question": "Exact interactive signup fields on dashboard.render.com/register.",
      "impact": "Could add undocumented form fields before the first Dashboard session.",
      "evidence_needed": "The tutorial says signup is fast and free without publishing the interactive field contract."
    }
  ],
  "counts": null
}
